pipe_helper/__init__.py
pgx_pipe_helper-0.0.4.dist-info/LICENSE
pgx_pipe_helper-0.0.4.dist-info/METADATA
pgx_pipe_helper-0.0.4.dist-info/WHEEL
pgx_pipe_helper-0.0.4.dist-info/top_level.txt
pgx_pipe_helper-0.0.4.dist-info/RECORD
